dldock/__init__.py
dldock/dldock.py
dldock/utils.py
dldock-0.0.1.dist-info/LICENSE
dldock-0.0.1.dist-info/METADATA
dldock-0.0.1.dist-info/WHEEL
dldock-0.0.1.dist-info/top_level.txt
dldock-0.0.1.dist-info/RECORD
