Metadata-Version: 2.1
Name: dldock
Version: 0.0.1
Summary: Shared Library Handler Based on Ctypes
Author: Sean West
License: MIT
Keywords: shared library handler
Requires-Python: >=3.8
License-File: LICENSE
